sctokenizer/__init__.py
sctokenizer/c_tokenizer.py
sctokenizer/cpp_tokenizer.py
sctokenizer/java_tokenizer.py
sctokenizer/main.py
sctokenizer/php_tokenizer.py
sctokenizer/python_tokenizer.py
sctokenizer/source.py
sctokenizer/token.py
sctokenizer/tokenizer.py
sctokenizer/assets/__init__.py
sctokenizer/assets/c_keywords.py
sctokenizer/assets/c_operators.py
sctokenizer/assets/cpp_keywords.py
sctokenizer/assets/cpp_operators.py
sctokenizer/assets/java_keywords.py
sctokenizer/assets/java_operators.py
sctokenizer/assets/php_keywords.py
sctokenizer/assets/php_operators.py
sctokenizer/assets/python_keywords.py
sctokenizer/assets/python_operators.py
sctokenizer-0.0.8.dist-info/LICENSE
sctokenizer-0.0.8.dist-info/METADATA
sctokenizer-0.0.8.dist-info/WHEEL
sctokenizer-0.0.8.dist-info/top_level.txt
sctokenizer-0.0.8.dist-info/RECORD
