Metadata-Version: 2.1
Name: sctokenizer
Version: 0.0.8
Summary: A Source Code Tokenizer
Author: Ngoc Bui
Author-email: ngocjr7@gmail.com
Project-URL: Bug Tracker, https://github.com/ngocjr7/sctokenizer/issues
Project-URL: Documentation, https://github.com/ngocjr7/sctokenizer/blob/master/README.md
Project-URL: Source Code, https://github.com/ngocjr7/sctokenizer
Requires-Python: >=3.6
License-File: LICENSE
